bringer
