Metadata-Version: 2.1
Name: bringer
Version: 0.1.0
Summary: You can find the basic and usable scripts, code blocks or informations via using your command line with bringer
Home-page: https://github.com/bilgehannal/bringer
Author: Bilgehan NAL
Author-email: bilgehannal@gmail.com
License: MIT
Keywords: programming,helper,find
Platform: UNKNOWN
Classifier: Development Status :: 3 - Alpha
Classifier: Intended Audience :: Developers
Classifier: Topic :: Software Development :: Build Tools
Classifier: License :: OSI Approved :: MIT License
Classifier: Programming Language :: Python :: 3
Classifier: Programming Language :: Python :: 3.4
Classifier: Programming Language :: Python :: 3.5
Classifier: Programming Language :: Python :: 3.6
Classifier: Programming Language :: Python :: 3.7
Classifier: Programming Language :: Python :: 3.8
Classifier: Programming Language :: Python :: 3.9
